{
 "actions": [],
 "allow_rename": 1,
 "creation": "2023-06-08 12:26:51.798533",
 "doctype": "DocType",
 "editable_grid": 1,
 "engine": "InnoDB",
 "field_order": [
  "resource",
  "name1",
  "mobile_no",
  "address"
 ],
 "fields": [
  {
   "fieldname": "resource",
   "fieldtype": "Select",
   "in_list_view": 1,
   "label": "Resource",
   "options": "Supervisor\nHelper\nOperator"
  },
  {
   "fieldname": "name1",
   "fieldtype": "Data",
   "in_list_view": 1,
   "label": "Name"
  },
  {
   "fieldname": "mobile_no",
   "fieldtype": "Data",
   "in_list_view": 1,
   "label": "Mobile no",
   "options": "Phone"
  },
  {
   "fieldname": "address",
   "fieldtype": "Small Text",
   "in_list_view": 1,
   "label": "Address"
  }
 ],
 "index_web_pages_for_search": 1,
 "istable": 1,
 "links": [],
 "modified": "2023-06-08 12:26:51.798533",
 "modified_by": "Administrator",
 "module": "Migoo CRM",
 "name": "Resource Details",
 "owner": "Administrator",
 "permissions": [],
 "sort_field": "modified",
 "sort_order": "DESC",
 "states": []
}